deepgram/__init__.py
deepgram/connection.py
deepgram/version.py
deepgram_brain-0.1.1.dist-info/DESCRIPTION.rst
deepgram_brain-0.1.1.dist-info/METADATA
deepgram_brain-0.1.1.dist-info/RECORD
deepgram_brain-0.1.1.dist-info/WHEEL
deepgram_brain-0.1.1.dist-info/metadata.json
deepgram_brain-0.1.1.dist-info/top_level.txt
