Metadata-Version: 2.0
Name: deepgram-brain
Version: 0.1.1
Summary: Deepgram Brain API client
Home-page: https://github.com/deepgram/deepgram-brain-python
Author: Jeff Ward
Author-email: jeff.ward@deepgram.com
License: Apache Software License (http://www.apache.org/licenses/LICENSE-2.0)
Download-URL: https://github.com/deepgram/deepgram-brain-python/archive/0.1.1.tar.gz
Keywords: deepgram,transcription,audio,deep learning,speech,awesome
Platform: UNKNOWN
Classifier: Intended Audience :: Developers
Classifier: Topic :: System :: Networking
Classifier: Topic :: Office/Business
Classifier: Programming Language :: Python :: 3
Classifier: Programming Language :: Python :: 3.5
Classifier: Programming Language :: Python :: 3.6
Requires-Dist: requests
